[{"departure":{"date":"2025-10-29T00:00:00.000Z","time":"10:00"},"arrival":{"date":"2025-10-29T00:00:00.000Z","time":"12:30"},"seatMatrix":{"rows":40,"columns":10,"occupiedSeats":[]},"discount":{"hasDiscount":true,"discountType":"percentage","discountValue":12,"discountStartDate":"2025-10-30T00:00:00.000Z","discountEndDate":"2025-11-05T00:00:00.000Z"},"_id":"68f67026122cf5d8539b4575","airlineId":"68f66eec122cf5d8539b4563","airline":"Air India","flightNumber":"AI-601","source":"Delhi","destination":"Goa","duration":150,"stops":0,"class":"Economy","price":16700,"totalSeats":180,"availableSeats":180,"operatingDays":["wed","fri","sun"],"isActive":true,"aircraftType":"Airbus A320","baggageAllowance":"20 kg check-in + 7kg cabin","createdAt":"2025-10-28T12:00:00.000Z","__v":0,"calculatedDeparture":{"date":"2025-11-01T18:30:00.000Z","time":"10:00"},"calculatedArrival":{"date":"2025-11-02T07:00:00.000Z","time":"12:30"},"searchDate":null},{"departure":{"date":"2025-11-25T00:00:00.000Z","time":"12:20"},"arrival":{"date":"2025-11-25T00:00:00.000Z","time":"14:50"},"seatMatrix":{"rows":40,"columns":10,"occupiedSeats":[]},"discount":{"hasDiscount":true,"discountType":"fixed","discountValue":2000,"discountStartDate":"2025-11-26T00:00:00.000Z","discountEndDate":"2025-12-02T00:00:00.000Z"},"_id":"68f67041122cf5d8539b4590","airlineId":"68fb91156c8f3e0429290320","airline":"Vistara","flightNumber":"VI-1701","source":"Delhi","destination":"Goa","duration":150,"stops":0,"class":"Business","price":24500,"totalSeats":88,"availableSeats":88,"operatingDays":["wed","fri","sun"],"isActive":true,"aircraftType":"Airbus A320neo","baggageAllowance":"32 kg check-in + 12kg cabin","createdAt":"2025-11-24T22:25:00.000Z","__v":0,"calculatedDeparture":{"date":"2025-11-01T18:30:00.000Z","time":"12:20"},"calculatedArrival":{"date":"2025-11-02T09:20:00.000Z","time":"14:50"},"searchDate":null},{"departure":{"date":"2025-11-05T00:00:00.000Z","time":"12:30"},"arrival":{"date":"2025-11-05T00:00:00.000Z","time":"15:00"},"seatMatrix":{"rows":40,"columns":10,"occupiedSeats":[]},"discount":{"hasDiscount":false,"discountType":"percentage","discountValue":null,"discountStartDate":null,"discountEndDate":null},"_id":"68f67052122cf5d8539b45a1","airlineId":"68fcae9a29da001550194563","airline":"Akasa Air","flightNumber":"AA-201","source":"Delhi","destination":"Goa","duration":150,"stops":0,"class":"Economy","price":11200,"totalSeats":192,"availableSeats":192,"operatingDays":["wed","fri","sun"],"isActive":true,"aircraftType":"Boeing 737 MAX","baggageAllowance":"15 kg check-in + 7kg cabin","createdAt":"2025-10-25T17:00:00.000Z","__v":0,"calculatedDeparture":{"date":"2025-11-01T18:30:00.000Z","time":"12:30"},"calculatedArrival":{"date":"2025-11-02T09:30:00.000Z","time":"15:00"},"searchDate":null},{"departure":{"date":"2025-11-14T00:00:00.000Z","time":"06:15"},"arrival":{"date":"2025-11-14T00:00:00.000Z","time":"08:45"},"seatMatrix":{"columns":10,"occupiedSeats":["7A"],"rows":40},"discount":{"hasDiscount":true,"discountType":"fixed","discountValue":900,"discountStartDate":"2025-11-15T00:00:00.000Z","discountEndDate":"2025-11-21T00:00:00.000Z"},"_id":"68f6705b122cf5d8539b45aa","airlineId":"68fcade529da001550194554","airline":"IndiGo Aviation","flightNumber":"IA-401","source":"Delhi","destination":"Goa","duration":150,"stops":0,"class":"Economy","price":10200,"totalSeats":180,"availableSeats":179,"operatingDays":["mon","wed","fri","sun"],"isActive":true,"aircraftType":"Airbus A320neo","baggageAllowance":"15 kg check-in + 7kg cabin","createdAt":"2025-10-25T21:30:00.000Z","__v":2,"calculatedDeparture":{"date":"2025-11-01T18:30:00.000Z","time":"06:15"},"calculatedArrival":{"date":"2025-11-02T03:15:00.000Z","time":"08:45"},"searchDate":null}]